pydecs/__init__.py
pydecs/aux_EdefCorrection_VASP.py
pydecs/aux_check_equilibrium_phases.py
pydecs/aux_convDOS.py
pydecs/aux_convGasEne.py
pydecs/aux_dpath.py
pydecs/aux_plot_defectdata.py
pydecs/aux_post.py
pydecs/aux_prep.py
pydecs/aux_runSupport.py
pydecs/common.py
pydecs/defects.py
pydecs/eqcond.py
pydecs/host.py
pydecs/inout.py
pydecs/pydecs.py
pydecs/reference_phases.py
pydecs/solver.py
pydecs-2025.12.18.dist-info/licenses/LICENSE.txt
pydecs-2025.12.18.dist-info/METADATA
pydecs-2025.12.18.dist-info/WHEEL
pydecs-2025.12.18.dist-info/entry_points.txt
pydecs-2025.12.18.dist-info/top_level.txt
pydecs-2025.12.18.dist-info/RECORD
