Metadata-Version: 2.4
Name: pydecs
Version: 2025.12.18
Summary: This tool enables us to analyze equilibrium concentrations of point and complex defects in crystalline solids
Home-page: https://gitlab.com/tkog/pydecs
Author: Takafumi Ogawa
Author-email: takafumi.ogawa.1+pydecs@gmail.com
License: Apache-2.0
Classifier: Intended Audience :: Science/Research
Classifier: Topic :: Scientific/Engineering :: Chemistry
Classifier: Topic :: Scientific/Engineering :: Physics
License-File: LICENSE.txt
Requires-Dist: numpy
Requires-Dist: scipy
Requires-Dist: matplotlib
Requires-Dist: toml
Requires-Dist: pathos
Provides-Extra: extra
Requires-Dist: pymatgen; extra == "extra"
Requires-Dist: pymatgen-analysis-defects; extra == "extra"
Requires-Dist: pandas; extra == "extra"
Requires-Dist: networkx; extra == "extra"
Requires-Dist: bvlain; extra == "extra"
Requires-Dist: ase; extra == "extra"
Dynamic: license-file
